ofxstatement_be_bnp-0.1.4-py3.7-nspkg.pth
ofxstatement/plugins/bnp.py
ofxstatement_be_bnp-0.1.4.dist-info/LICENSE
ofxstatement_be_bnp-0.1.4.dist-info/METADATA
ofxstatement_be_bnp-0.1.4.dist-info/WHEEL
ofxstatement_be_bnp-0.1.4.dist-info/entry_points.txt
ofxstatement_be_bnp-0.1.4.dist-info/namespace_packages.txt
ofxstatement_be_bnp-0.1.4.dist-info/top_level.txt
ofxstatement_be_bnp-0.1.4.dist-info/zip-safe
ofxstatement_be_bnp-0.1.4.dist-info/RECORD
