Metadata-Version: 2.1
Name: ofxstatement-be-bnp
Version: 0.1.4
Summary: ofxstatement plugin for parsing Belgian BNP Paribas Fortis bank's CSV statements to OFX
Home-page: https://github.com/bfrisque/ofxstatement-be-bnp
Author: Benoit Frisque
Author-email: benoitfrisque@gmail.com
License: GPLv3
Keywords: ofx,banking,statement,bnp,csv
Platform: UNKNOWN
Classifier: Development Status :: 5 - Production/Stable
Classifier: Programming Language :: Python :: 3
Classifier: Natural Language :: English
Classifier: Topic :: Office/Business :: Financial :: Accounting
Classifier: Topic :: Utilities
Classifier: Environment :: Console
Classifier: Operating System :: OS Independent
Classifier: License :: OSI Approved :: GNU General Public License v3 (GPLv3)
Requires-Dist: ofxstatement
